{"text": "压电发电装置及其发电方法", "label": {"keyword": {"发电装置": [[2, 5]]}}}
{"text": "一种纳米氧化物掺杂硼酸铁锂正极材料的制备方法", "label": {"keyword": {"正极材料": [[13, 16]]}}}
{"text": "一种高浓度有机无机混合废水处理回收方法", "label": {"keyword": {"有机无机": [[5, 8]]}}}
{"text": "一种防止太平芫荽杂菌污染的酸洗方法", "label": {"keyword": {"杂菌": [[8, 9]]}}}
{"text": "一种新型精密光纤激光打标机", "label": {"keyword": {"激光打标机": [[8, 12]]}}}
{"text": "一种ONU光模块发射端光功率监测方法", "label": {"keyword": {"光功率监测": [[11, 15]]}}}
{"text": "板坯连铸中间包盖用吹氩装置", "label": {"keyword": {"连铸中间包": [[2, 6]], "板坯连铸": [[0, 3]]}}}
{"text": "一种利用可见光促进蛋白质结晶的方法和装置", "label": {"keyword": {"蛋白质结晶": [[9, 13]]}}}
{"text": "集约化烤房烟门自动控制装置", "label": {"keyword": {"自动控制装置": [[7, 12]]}}}
{"text": "一种磁保持继电器电气寿命测试装置", "label": {"keyword": {"磁保持继电器": [[2, 7]]}}}
{"text": "一种用于高温高压水蒸气氧化腐蚀试验的高压釜系统", "label": {"keyword": {"高温高压水": [[4, 8]], "高温高压": [[4, 7]]}}}
{"text": "一种农产品产销决策方法,装置及系统", "label": {"keyword": {"农产品": [[2, 4]], "决策方法": [[7, 10]]}}}
{"text": "汽车空调控制板故障诊断系统及方法", "label": {"keyword": {"故障诊断系统": [[7, 12]]}}}
{"text": "线位移和索力监测的损伤电缆集中载荷渐进识别方法", "label": {"keyword": {"索力监测": [[4, 7]]}}}
{"text": "腹拱式拱桥柔性减震连续桥面铺装结构体系及其施工技术", "label": {"keyword": {"连续桥面": [[9, 12]], "施工技术": [[21, 24]]}}}
{"text": "港口电网电能质量监测系统指标分级显示方法", "label": {"keyword": {"电能质量监测": [[4, 9]]}}}
{"text": "基于RTDS脚本的小电流接地选线装置闭环测试方法", "label": {"keyword": {"选线装置": [[14, 17]]}}}
{"text": "一种用于空气质量检测的无线传感器网络系统", "label": {"keyword": {"无线传感器网络": [[11, 17]]}}}
{"text": "呼出气酒精浓度检测报警装置", "label": {"keyword": {"浓度检测": [[5, 8]]}}}
{"text": "一种用于打印产品的在线计数装置,数字化管理系统和方法", "label": {"keyword": {"数字化管理系统": [[16, 22]]}}}
{"text": "金属熔体双向旋转磁场搅拌净化装置", "label": {"keyword": {"旋转磁场": [[6, 9]]}}}
{"text": "局部脑组织血氧饱和度绝对量检测装置及方法", "label": {"keyword": {"血氧饱和度": [[5, 9]]}}}
{"text": "耐酸酯加氢催化剂及其制备方法和应用,酯加氢方法", "label": {"keyword": {"方法和应用": [[12, 16]], "加氢催化剂": [[3, 7]]}}}
{"text": "基于故障行波沿线分布特征的T形线路多端行波定位方法", "label": {"keyword": {"行波定位": [[19, 22]]}}}
{"text": "一种基于细菌生长的细菌快速显微镜检查方法", "label": {"keyword": {"显微镜检查": [[13, 17]]}}}
{"text": "一种石蜡相变储能微胶囊及其制备方法和应用", "label": {"keyword": {"相变储能": [[4, 7]]}}}
{"text": "一种环形磁性随机存取存储器单元结构的制造方法", "label": {"keyword": {"磁性随机存取存储器": [[4, 12]]}}}
{"text": "一种具有抗淋巴瘤作用的复方药物组合物及其用途", "label": {"keyword": {"药物组合物": [[13, 17]]}}}
{"text": "用于电力营销的自助一体机", "label": {"keyword": {"电力营销": [[2, 5]]}}}
{"text": "一种载银沸石吸附剂的制备方法", "label": {"keyword": {"载银沸石": [[2, 5]]}}}
{"text": "一种复杂形状薄板的局部减薄放电加工装置及加工工艺", "label": {"keyword": {"放电加工": [[13, 16]]}}}
{"text": "还原石墨烯-聚苯胺-邻氨基苯酚-钯复合改性玻碳电极的制备方法及其在水中溴酸盐检测中的应用", "label": {"keyword": {"改性玻碳电极": [[19, 24]], "玻碳电极": [[21, 24]]}}}
{"text": "基于水合物法的大型地下储气库及其地下储气库方法", "label": {"keyword": {"地下储气库": [[9, 13], [16, 20]]}}}
{"text": "配电网变压器低压绕组变形在线监测装置及方法", "label": {"keyword": {"在线监测装置": [[12, 17]]}}}
{"text": "一种污泥中多环芳烃的测定方法", "label": {"keyword": {"芳烃": [[7, 8]], "多环芳烃": [[5, 8]], "多环芳烃": [[5, 8]]}}}
{"text": "管道内氧化皮堆积的定量检测方法及检测仪", "label": {"keyword": {"定量检测方法": [[9, 14]]}}}
{"text": "外膜机理大容量光催化废水降解反应器", "label": {"keyword": {"废水降解": [[10, 13]]}}}
{"text": "钢管混凝土支撑压力装置", "label": {"keyword": {"钢管混凝土": [[0, 4]]}}}
{"text": "一种液态重金属冷却自然循环池反应器内部辅助加热系统", "label": {"keyword": {"辅助加热系统": [[19, 24]]}}}
{"text": "一种模拟深水环境爆炸试验容器的静压试验装置", "label": {"keyword": {"深水环境": [[4, 7]]}}}
{"text": "蛋白质色谱纯化介质的清洗方法", "label": {"keyword": {"色谱纯化": [[3, 6]]}}}
{"text": "一种熔融气化炉圆顶温度控制方法", "label": {"keyword": {"温度控制方法": [[9, 14]]}}}
{"text": "一种α,β-不饱和羰基化合物的制备方法", "label": {"keyword": {"不饱和羰基化合物": [[6, 13]]}}}
{"text": "一种降解高分子多环芳烃的海洋菌液及其制备方法", "label": {"keyword": {"芳烃": [[9, 10]]}}}
{"text": "一种压载水舱超压保护结构", "label": {"keyword": {"超压保护": [[6, 9]]}}}
{"text": "一种高温稳定性无单斜相的四方氧化锆热障涂层材料及其制备方法", "label": {"keyword": {"高温稳定性": [[2, 6]], "热障涂层材料": [[17, 22]], "热障涂层": [[17, 20]]}}}
{"text": "一种复合轻骨料混凝土自保温砌块", "label": {"keyword": {"自保温砌块": [[10, 14]]}}}
{"text": "一种基于特征分布的遥感影像质量评价方法", "label": {"keyword": {"遥感影像": [[9, 12]]}}}
{"text": "一种甲烷氧化菌液的制备方法,填埋场覆盖材料及减少填埋场甲烷排放的方法", "label": {"keyword": {"甲烷氧化菌": [[2, 6]], "甲烷氧化菌": [[2, 6]]}}}
{"text": "膦酸自组装单层作为高性能有机薄膜晶体管的介电表面", "label": {"keyword": {"自组装单层": [[2, 6]], "有机薄膜晶体管": [[12, 18]], "自组装单层": [[2, 6]]}}}
{"text": "多取代黄烷酮衍生物及其制备和应用", "label": {"keyword": {"黄烷酮衍生物": [[3, 8]]}}}
{"text": "一种用于氨硼烷水解制氢的碳载Ni 3 B复合催化剂", "label": {"keyword": {"水解制氢": [[7, 10]]}}}
{"text": "浸没式光刻机浸液输送系统控制序列的模型匹配方法", "label": {"keyword": {"浸没式光刻": [[0, 4]], "模型匹配方法": [[17, 22]]}}}
{"text": "锗烷型倍半萜衍生物及其制备方法和应用", "label": {"keyword": {"方法和应用": [[13, 17]], "倍半萜衍生物": [[3, 8]]}}}
{"text": "一种组装式野外移动遥感监测系统", "label": {"keyword": {"遥感监测": [[9, 12]]}}}
{"text": "一种直/斜圆柱齿轮的精密成形方法", "label": {"keyword": {"斜圆柱齿轮": [[4, 8]]}}}
{"text": "基于屏式两性离子交换膜电极的电化学除湿装置", "label": {"keyword": {"离子交换膜": [[6, 10]], "两性离子交换膜": [[4, 10]], "离子交换膜": [[6, 10]]}}}
{"text": "一种可以电解水产生氢气的电池装置", "label": {"keyword": {"电解水": [[4, 6]]}}}
{"text": "一种制备手性选择性和导电选择性单壁碳纳米管的催化剂,制备方法和应用", "label": {"keyword": {"单壁碳纳米管": [[15, 20]], "方法和应用": [[28, 32]], "壁碳纳米管": [[16, 20]], "单壁碳纳米管": [[15, 20]], "壁碳纳米管": [[16, 20]]}}}
{"text": "家畜微电脑自动控制喷雾降温装置", "label": {"keyword": {"微电脑自动控制": [[2, 8]], "电脑自动控制": [[3, 8]]}}}
{"text": "一种以太网供电系统的温度控制方法和装置", "label": {"keyword": {"温度控制方法": [[10, 15]]}}}
{"text": "CFC-113催化加氢脱氯制备三氟氯乙烯的催化剂及其制备方法", "label": {"keyword": {"三氟氯乙烯": [[15, 19]]}}}
{"text": "一种结晶器振动同步控制方法", "label": {"keyword": {"振动同步": [[5, 8]], "同步控制": [[7, 10]], "结晶器振动": [[2, 6]], "同步控制方法": [[7, 12]]}}}
{"text": "一种智能识别卡的自动分拣收集方法", "label": {"keyword": {"智能识别": [[2, 5]]}}}
{"text": "三自由度直升机的直接自适应重构控制方法", "label": {"keyword": {"重构控制": [[13, 16]]}}}
{"text": "直流电加热炉炉衬膨胀变形保护电路", "label": {"keyword": {"电加热炉": [[2, 5]]}}}
{"text": "教室照明节能集中控制系统", "label": {"keyword": {"集中控制系统": [[6, 11]]}}}
{"text": "一种氧化铜纳米线的制备方法及其在锂电池负极中的应用", "label": {"keyword": {"氧化铜纳米线": [[2, 7]]}}}
{"text": "一种含硫磷酸铵缓释肥及其制备方法", "label": {"keyword": {"缓释肥": [[7, 9]]}}}
{"text": "极硬矸石复杂结构煤层综采技术", "label": {"keyword": {"综采技术": [[10, 13]], "综采": [[10, 11]]}}}
{"text": "基于频分复用的可见光高精度室内定位方法", "label": {"keyword": {"频分复用": [[2, 5]]}}}
{"text": "一种固相萃取湿法冶金锌尾矿渣中钴的回收方法", "label": {"keyword": {"固相萃取": [[2, 5]]}}}
{"text": "一种轴流导叶可调液力变矩器", "label": {"keyword": {"液力变矩器": [[8, 12]], "导叶可调": [[4, 7]], "可调液力变矩器": [[6, 12]]}}}
{"text": "实现液压机超低速稳定运行的电液控制系统", "label": {"keyword": {"电液控制": [[13, 16]], "电液控制系统": [[13, 18]]}}}
{"text": "硬岩隧道掘进机刀盘驱动系统刀具磨损实时估计方法", "label": {"keyword": {"隧道掘进机": [[2, 6]]}}}
{"text": "一种真空绝热板真空测量装置", "label": {"keyword": {"真空绝热板": [[2, 6]], "真空绝热板": [[2, 6]]}}}
{"text": "一种合成宽或双分子量分布聚烯烃的催化剂及制备方法", "label": {"keyword": {"分子量分布": [[7, 11]]}}}
{"text": "一种智能变电站的智能报警及综合判断方法", "label": {"keyword": {"综合判断方法": [[13, 18]], "综合判断": [[13, 16]], "智能变电站": [[2, 6]]}}}
{"text": "一种基于强相关的动态加权红外光谱特征选择方法", "label": {"keyword": {"特征选择方法": [[16, 21]]}}}
{"text": "一种基于键合技术的光学读出红外探测器阵列的制造方法", "label": {"keyword": {"红外探测器阵列": [[13, 19]]}}}
{"text": "一种游霉素发酵生产的方法", "label": {"keyword": {"发酵生产": [[5, 8]]}}}
{"text": "一种基于视频采集的多目标室内定位系统及定位方法", "label": {"keyword": {"室内定位系统": [[12, 17]]}}}
{"text": "基于BCM控制的双区自动空调控制系统", "label": {"keyword": {"空调控制系统": [[12, 17]], "空调控制": [[12, 15]]}}}
{"text": "基于气动控制技术的肢体残疾人驾驶辅助系统", "label": {"keyword": {"驾驶辅助系统": [[14, 19]]}}}
{"text": "一种用含油量测定沥青高温性能的方法", "label": {"keyword": {"高温性能": [[10, 13]]}}}
{"text": "复合卡拉胶酶及其制备硒化卡拉胶寡糖的方法", "label": {"keyword": {"卡拉胶寡糖": [[12, 16]]}}}
{"text": "一种去除高温烟气中二恶英的装置", "label": {"keyword": {"高温烟气": [[4, 7]]}}}
{"text": "基于楔形导光板的傅里叶变换联合相关指纹识别装置", "label": {"keyword": {"指纹识别": [[17, 20]]}}}
{"text": "基于XDM2510H的无线HART智能压力变送器", "label": {"keyword": {"智能压力变送器": [[17, 23]]}}}
{"text": "消除伺服系统抖动的电磁装置及方法", "label": {"keyword": {"电磁装置": [[9, 12]]}}}
{"text": "一种基于压缩感知的井下数据采集与处理方法", "label": {"keyword": {"数据采集与处理": [[11, 17]], "采集与处理": [[13, 17]]}}}
{"text": "一种基于微博的广告推荐方法及系统", "label": {"keyword": {"推荐方法": [[9, 12]]}}}
{"text": "PCI从设备核心控制模块应用于高速运动控制系统", "label": {"keyword": {"运动控制系统": [[17, 22]]}}}
{"text": "APC基因的应用及其单核苷酸多态性", "label": {"keyword": {"核苷酸多态性": [[11, 16]], "单核苷酸多态性": [[10, 16]], "单核苷酸多态性": [[10, 16]], "核苷酸多态性": [[11, 16]]}}}
{"text": "盐酸美西律缓释制剂及制备方法", "label": {"keyword": {"缓释制剂": [[5, 8]], "盐酸美西律": [[0, 4]]}}}
{"text": "聚酮化合物及其制备方法和应用", "label": {"keyword": {"方法和应用": [[9, 13]]}}}
{"text": "一种基于安全基线的工控机安全防护系统及方法", "label": {"keyword": {"安全防护系统": [[12, 17]]}}}
{"text": "一种闭孔泡沫镁合金复合材料的制备方法", "label": {"keyword": {"泡沫镁合金": [[4, 8]]}}}
{"text": "基于二氧化钛纳米棒光散射薄膜电极的染料敏化太阳能电池及其制备方法", "label": {"keyword": {"染料敏化太阳能电池": [[17, 25]], "敏化太阳能电池": [[19, 25]], "敏化太阳能电池": [[19, 25]]}}}
{"text": "一种具有稳定紫色或蓝色发光特性的氧化锌纳米粒子的制备方法", "label": {"keyword": {"氧化锌纳米粒子": [[16, 22]], "氧化锌纳米粒子": [[16, 22]]}}}
{"text": "气动比例阀颤振补偿的一种参数设定方法", "label": {"keyword": {"气动比例阀": [[0, 4]]}}}
{"text": "一种结核感染的T细胞免疫检测抗原及其应用", "label": {"keyword": {"结核感染": [[2, 5]]}}}
{"text": "基于电动助力转向系统的无人驾驶汽车自动转向控制装置", "label": {"keyword": {"电动助力转向": [[2, 7]]}}}
{"text": "钢筋混凝土框架柱抗滞后破坏破碎", "label": {"keyword": {"钢筋混凝土框架柱": [[0, 7]]}}}
{"text": "一种基于弛豫铁电材料磁电传感器的前端放大电路", "label": {"keyword": {"铁电材料": [[6, 9]], "磁电传感器": [[10, 14]]}}}
{"text": "一种从低价棉籽油中制备低倾点润滑油添加剂的方法", "label": {"keyword": {"润滑油添加剂": [[14, 19]]}}}
{"text": "基于GPRS网络和综合识别网络的访问控制方法及装置", "label": {"keyword": {"综合识别": [[9, 12]]}}}
{"text": "一种仲酰胺季铵盐型羟丙基磷酸钠沥青乳化剂及其制备方法", "label": {"keyword": {"季铵盐": [[5, 7]]}}}
{"text": "一种两步湿法腈纶生产废水的处理方法", "label": {"keyword": {"生产废水": [[8, 11]]}}}
{"text": "基于射频隐身的分布式MIMO雷达发射信号优化设计方法", "label": {"keyword": {"射频隐身": [[2, 5]]}}}
{"text": "一种钨极氩弧焊与冷金属过渡焊复合热源焊接设备,方法及应用", "label": {"keyword": {"复合热源": [[14, 17]]}}}
{"text": "可见可缩回套囊鼻咽气道装置及其使用方法", "label": {"keyword": {"鼻咽气道": [[7, 10]]}}}
{"text": "一种碳纤维汽车空调滤清器", "label": {"keyword": {"汽车空调": [[5, 8]]}}}
{"text": "三相负载不平衡状态下配电变压器噪声监测方法及系统", "label": {"keyword": {"配电变压器": [[10, 14]]}}}
{"text": "一种高重复频率双腔准分子激光放电同步控制装置", "label": {"keyword": {"同步控制": [[16, 19]]}}}
{"text": "热连轧给水可视化控制装置", "label": {"keyword": {"热连轧": [[0, 2]]}}}
{"text": "一种基础仿生粘合剂聚丙烯酰胺水凝胶体系的制备方法", "label": {"keyword": {"聚丙烯酰胺水凝胶": [[9, 16]], "聚丙烯酰胺水凝胶": [[9, 16]]}}}
{"text": "一种预焙铝电解槽脱壳装置", "label": {"keyword": {"铝电解槽": [[4, 7]]}}}
{"text": "用于检测有机小分子化合物的铕铈共掺杂复合荧光传感材料的制备方法及应用", "label": {"keyword": {"有机小分子": [[4, 8]]}}}
{"text": "一种利用萘磺酸盐回收废液制备萘系分散剂的方法及用途", "label": {"keyword": {"萘磺酸": [[4, 6]]}}}
{"text": "一种耐摩擦色牢度实时检测装置及其检测方法", "label": {"keyword": {"耐摩擦色牢度": [[2, 7]]}}}
{"text": "一种黄芪总黄酮纳米水溶液的制备方法", "label": {"keyword": {"黄芪总黄酮": [[2, 6]]}}}
{"text": "杯芳烃衍生物在钾盐相转移催化反应中的应用", "label": {"keyword": {"杯芳烃衍生物": [[0, 5]], "杯芳烃衍生物": [[0, 5]], "相转移催化": [[9, 13]]}}}
{"text": "自动导引车无线控制系统", "label": {"keyword": {"无线控制系统": [[5, 10]]}}}
{"text": "双-6-氧-(3-脱氧柠檬酸单酯-4)-β-环糊精高效液相色谱柱材料的制备及应用", "label": {"keyword": {"色谱柱": [[29, 31]], "高效液相色谱": [[25, 30]], "液相色谱": [[27, 30]]}}}
{"text": "使用组合绝缘子的输电线路塔", "label": {"keyword": {"输电线路塔": [[8, 12]]}}}
{"text": "适用于纳米器件制造的硅化物工艺", "label": {"keyword": {"纳米器件制造": [[3, 8]]}}}
{"text": "一种聚合物包覆镍铝合金/硫复合电极材料的制备方法", "label": {"keyword": {"复合电极材料": [[13, 18]], "镍铝合金": [[7, 10]]}}}
{"text": "电磁阀永磁操作机构单向定位器", "label": {"keyword": {"永磁操作机构": [[3, 8]]}}}
{"text": "一种高炉喷煤助燃剂及其制备方法和应用", "label": {"keyword": {"高炉喷煤": [[2, 5]]}}}
{"text": "一种以滑石粉纳米抗菌粉为载体制备抗菌塑料制品的方法", "label": {"keyword": {"抗菌塑料": [[16, 19]]}}}
{"text": "基于仿真的单晶涡轮叶片精密铸造工艺参数优化方法", "label": {"keyword": {"参数优化方法": [[17, 22]]}}}
{"text": "混凝土内置钢管活性粉末混凝土复合柱", "label": {"keyword": {"钢管活性粉末混凝土": [[5, 13]], "活性粉末混凝土": [[7, 13]]}}}
{"text": "城市地铁列车用气体储能机电转换减震发电装置", "label": {"keyword": {"发电装置": [[17, 20]], "机电转换": [[11, 14]]}}}
{"text": "全髋关节置换术髋臼下缘冷光源牵开器", "label": {"keyword": {"全髋关节置换术": [[0, 6]]}}}
{"text": "万能材料试验机加热保温装置", "label": {"keyword": {"万能材料试验机": [[0, 6]], "材料试验机": [[2, 6]]}}}
{"text": "一种木糖转化生产木糖醇的活菌制剂及其应用", "label": {"keyword": {"活菌制剂": [[12, 15]], "及其应用": [[16, 19]]}}}
{"text": "一种双离合自动变速器润滑流量调节装置", "label": {"keyword": {"自动变速器": [[5, 9]], "双离合自动变速器": [[2, 9]]}}}
{"text": "一种用于直流联网的高效非晶合金中频变压器", "label": {"keyword": {"中频变压器": [[15, 19]]}}}
{"text": "基于TMX320F28335浮点DSP的两轴光电跟踪系统", "label": {"keyword": {"光电跟踪": [[22, 25]]}}}
{"text": "考虑卸载电路的直驱风电场等效建模方法", "label": {"keyword": {"等效建模方法": [[12, 17]]}}}
{"text": "一种ZSM-48/Y复合分子筛的制备方法", "label": {"keyword": {"复合分子筛": [[10, 14]]}}}
{"text": "高低温复式风机盘管机组", "label": {"keyword": {"高低温": [[0, 2]]}}}
{"text": "一种取向硅钢在高温退火时涂有MgO涂层的固定方法", "label": {"keyword": {"高温退火": [[7, 10]], "取向硅钢": [[2, 5]], "高温退火": [[7, 10]], "高温退火": [[7, 10]]}}}
{"text": "一种三维多孔结构铝集电体的制备方法", "label": {"keyword": {"三维多孔": [[2, 5]], "三维多孔结构": [[2, 7]]}}}
{"text": "基于多特征提取的雷达脉冲重复间隔调制识别方法", "label": {"keyword": {"脉冲重复间隔": [[10, 15]]}}}
{"text": "使用同步辐射光源原位成像的疲劳试验机及试验方法", "label": {"keyword": {"同步辐射光源": [[2, 7]], "同步辐射": [[2, 5]], "同步辐射": [[2, 5]], "疲劳试验机": [[13, 17]]}}}
{"text": "一种汽车防撞钢梁探伤仪", "label": {"keyword": {"汽车防撞": [[2, 5]]}}}
{"text": "一种VEGF靶向治疗药物的生物活性检测方法", "label": {"keyword": {"靶向治疗药物": [[6, 11]]}}}
{"text": "一种石油化工用重油轻质加氢裂化装置", "label": {"keyword": {"石油化工": [[2, 5]]}}}
{"text": "带温度补偿的光纤布拉格光栅磁场传感器", "label": {"keyword": {"温度补偿": [[1, 4]]}}}
{"text": "一种油气管道山洪灾害监测系统", "label": {"keyword": {"山洪灾害": [[6, 9]], "油气管道": [[2, 5]]}}}
{"text": "多次热循环下涡轮叶片“嬧媡”热障涂层危险区预测方法", "label": {"keyword": {"热障涂层": [[14, 17]]}}}
{"text": "LED用硅酸镥绿色荧光材料及其制备方法和应用", "label": {"keyword": {"方法和应用": [[17, 21]]}}}
{"text": "具有混合电磁力弹簧的压电泵", "label": {"keyword": {"电磁力": [[4, 6]]}}}
{"text": "一种治疗股骨头缺血性坏死的药物及其制备方法", "label": {"keyword": {"股骨头缺血性坏死": [[4, 11]], "股骨头缺血性坏死": [[4, 11]], "股骨头缺血性坏死": [[4, 11]]}}}
{"text": "一种双翼仿生蝴蝶扑翼飞机", "label": {"keyword": {"扑翼飞机": [[8, 11]]}}}
{"text": "电力工程施工应急车辆专用集装箱", "label": {"keyword": {"电力工程": [[0, 3]]}}}
{"text": "激光对射式工业机械手工作点坐标示教工具", "label": {"keyword": {"工业机械手": [[5, 9]]}}}
{"text": "一种光照均匀的双面镜导光栅光伏温室", "label": {"keyword": {"光伏温室": [[13, 16]]}}}
{"text": "一种用于高速伺服电机的霍尔传感器输出信号处理电路", "label": {"keyword": {"信号处理电路": [[18, 23]]}}}
{"text": "一种轻质泡沫陶瓷管道保温层结构", "label": {"keyword": {"保温层": [[10, 12]]}}}
{"text": "一种用于分析水溶液中蛋白质二级结构的傅里叶变换红外光谱样品制备方法", "label": {"keyword": {"蛋白质二级结构": [[10, 16]], "蛋白质二级结构": [[10, 16]], "样品制备方法": [[27, 32]]}}}
{"text": "LED照明装置及PWM直流电源控制电路", "label": {"keyword": {"电源控制电路": [[13, 18]]}}}
{"text": "微污染原水预处理系列曝气生物滤池工艺", "label": {"keyword": {"曝气生物滤池": [[10, 15]], "微污染原水": [[0, 4]], "原水预处理": [[3, 7]], "曝气生物滤池": [[10, 15]]}}}
{"text": "一种智能植保无人机控制管理系统及其控制方法", "label": {"keyword": {"无人机": [[6, 8]], "植保无人机": [[4, 8]]}}}
{"text": "可变发射率粘合热控涂层的制备方法", "label": {"keyword": {"热控涂层": [[7, 10]]}}}
{"text": "一种腐蚀性产酸菌的培养方法", "label": {"keyword": {"产酸菌": [[5, 7]]}}}
{"text": "极地咽齿象的人工繁殖方法", "label": {"keyword": {"人工繁殖": [[6, 9]]}}}
{"text": "一种基于单片机的一氧化碳泄漏报警器", "label": {"keyword": {"单片机": [[4, 6]], "单片机": [[4, 6]]}}}
{"text": "基于交流电流直接控制的永磁同步电机弱磁控制系统", "label": {"keyword": {"永磁同步电机": [[11, 16]], "磁同步电机": [[12, 16]], "弱磁控制": [[17, 20]], "永磁同步": [[11, 14]]}}}
{"text": "一种锗量子点的制备方法", "label": {"keyword": {"锗量子点": [[2, 5]]}}}
{"text": "岩石断裂面任意角度剪切试验装置及试验方法", "label": {"keyword": {"岩石断裂面": [[0, 4]]}}}
{"text": "一种褐藻多糖的提取方法", "label": {"keyword": {"褐藻多糖": [[2, 5]]}}}
{"text": "一种分解磷化氢制备元素磷的催化剂及其制备与应用", "label": {"keyword": {"制备与应用": [[18, 22]]}}}
{"text": "一种铁矿石软化温度测量仪", "label": {"keyword": {"软化温度": [[5, 8]]}}}
{"text": "一种菊芋微生物发酵培养原料预处理方法", "label": {"keyword": {"微生物发酵": [[4, 8]]}}}
{"text": "一种去除四环素类物质的改性活性炭纤维棉的制备方法", "label": {"keyword": {"改性活性炭纤维": [[11, 17]], "改性活性炭": [[11, 15]], "活性炭纤维": [[13, 17]]}}}
{"text": "二氧化硅纳米磁性微球及其制备方法", "label": {"keyword": {"磁性微球": [[6, 9]]}}}
{"text": "生物质气化气雾化选择性非催化还原方法及所用锅炉", "label": {"keyword": {"选择性非催化还原": [[8, 15]]}}}
{"text": "一种高效液相色谱法测定柑橘类水果中酚类化合物的方法", "label": {"keyword": {"高效液相": [[2, 5]]}}}
{"text": "十二烷基三甲基氯化铵反胶束溶液提取大豆蛋白的方法", "label": {"keyword": {"反胶束溶液": [[10, 14]], "十二烷基三甲基氯化铵": [[0, 9]]}}}
{"text": "基于有机薄膜晶体管的透明变色多重防伪闪存器件及其制备方法和应用", "label": {"keyword": {"有机薄膜晶体管": [[2, 8]]}}}
{"text": "圆柱结构横向内孔加工装置", "label": {"keyword": {"圆柱结构": [[0, 3]]}}}
{"text": "MGB探针多重荧光定量PCR检测大肠杆菌O157", "label": {"keyword": {"荧光定量": [[7, 10]]}}}
{"text": "多级挡板复氧人工湿地污水处理系统及污水处理方法", "label": {"keyword": {"污水处理系统": [[10, 15]]}}}
{"text": "钯催化合成4-硝基三苯胺的方法", "label": {"keyword": {"钯催化合成": [[0, 4]]}}}
{"text": "microRNA-219试剂盒及其应用", "label": {"keyword": {"及其应用": [[15, 18]]}}}
{"text": "一种大规模制备Werethro内酯化学对照品的方法", "label": {"keyword": {"大规模制备": [[2, 6]], "化学对照品": [[17, 21]]}}}
{"text": "一种增强抗菌活性的猪链球菌噬菌体裂解酶及其制备方法", "label": {"keyword": {"抗菌活性": [[4, 7]]}}}
{"text": "超声与核磁共振图像融合腔内配准装置及其方法", "label": {"keyword": {"磁共振图像": [[4, 8]], "核磁共振图像": [[3, 8]], "核磁共振": [[3, 6]], "磁共振图像": [[4, 8]]}}}
{"text": "印刷电路板,实现方法和去除电子元件的方法", "label": {"keyword": {"印刷电路板": [[0, 4]], "电子元件": [[13, 16]]}}}
{"text": "碳纤维精细浸渍张力控制系统及控制方法", "label": {"keyword": {"张力控制系统": [[7, 12]]}}}
{"text": "三维模型的外观纹理合成方法及装置", "label": {"keyword": {"三维模型": [[0, 3]]}}}
{"text": "一种中央空调多向可调风阀", "label": {"keyword": {"中央空调": [[2, 5]], "中央空调": [[2, 5]]}}}
{"text": "一种用于蛋白质标记的水溶性近红外荧光探针及合成方法", "label": {"keyword": {"近红外荧光探针": [[13, 19]]}}}
{"text": "室内可见光通信功率优化方法", "label": {"keyword": {"室内可见光通信": [[0, 6]]}}}
{"text": "一种家畜中药饲料添加剂及其制备方法和应用", "label": {"keyword": {"方法和应用": [[15, 19]]}}}
{"text": "电阻应变测量的远程调零电路及调零方法", "label": {"keyword": {"电阻应变测量": [[0, 5]]}}}
{"text": "一种用于开关柜局部放电检测的地波信号测试装置", "label": {"keyword": {"局部放电检测": [[7, 12]]}}}
{"text": "一种微波制备双酚A印迹单片棒固相微萃取纤维的方法", "label": {"keyword": {"相微萃取": [[15, 18]], "固相微萃取": [[14, 18]], "固相微萃取": [[14, 18]]}}}
{"text": "有机废水活性炭纤维吸附装置和解吸装置", "label": {"keyword": {"活性炭纤维": [[4, 8]]}}}
{"text": "基于权限组件的工作流组件权限管理方法及装置", "label": {"keyword": {"权限管理": [[12, 15]]}}}
{"text": "具有快速瞬态响应的开关电源", "label": {"keyword": {"快速瞬态响应": [[2, 7]]}}}
{"text": "纯氧燃烧零气门二冲程高效微排放内燃机", "label": {"keyword": {"内燃机": [[15, 17]]}}}
{"text": "一种自动供水的太阳能热水器", "label": {"keyword": {"自动供水": [[2, 5]]}}}
{"text": "用于高压架空输电线路的机载 3D LiDAR 检测系统", "label": {"keyword": {"架空输电线路": [[4, 9]], "高压架空输电线路": [[2, 9]]}}}
{"text": "具有警示功能的多功能定位矿工服", "label": {"keyword": {"功能定位": [[8, 11]]}}}
{"text": "粗2,6-萘二甲酸氧化浆液的溶剂置换方法", "label": {"keyword": {"萘二甲酸": [[5, 8]]}}}
{"text": "一种2-取代苯基-4-芳基氨基喹唑啉衍生物及其制备方法和应用", "label": {"keyword": {"方法和应用": [[25, 29]], "喹唑啉衍生物": [[15, 20]], "喹唑啉衍生物": [[15, 20]]}}}
{"text": "基于图像识别技术的群控电梯智能调度装置", "label": {"keyword": {"群控电梯": [[9, 12]]}}}
{"text": "一种外转式纸浆浓度检测装置", "label": {"keyword": {"浓度检测": [[7, 10]]}}}
{"text": "油烟道油垢燃烧特性分析装置", "label": {"keyword": {"特性分析": [[7, 10]], "燃烧特性": [[5, 8]], "燃烧特性": [[5, 8]]}}}
{"text": "套筒式吸附器及其吸附和解吸CO 2的方法", "label": {"keyword": {"吸附和解吸": [[8, 12]]}}}
{"text": "具有融合码下标调制的多二进制差分混沌移位键控调制解调器", "label": {"keyword": {"差分混沌移位键控": [[14, 21]]}}}
{"text": "miRNA169h基因预测水稻白叶枯病", "label": {"keyword": {"水稻白叶枯病": [[13, 18]]}}}
{"text": "一种两档纯电动双离合变速器的传动系统", "label": {"keyword": {"双离合变速器": [[7, 12]]}}}
{"text": "复合海缆温升应变监测报警及故障分析方法", "label": {"keyword": {"故障分析方法": [[13, 18]]}}}
{"text": "一种用于驱动新能源汽车的永磁同步电机转子", "label": {"keyword": {"永磁同步电机": [[12, 17]], "永磁同步电机": [[12, 17]], "永磁同步": [[12, 15]]}}}
{"text": "粉体计量装置及混凝土搅拌站", "label": {"keyword": {"混凝土搅拌站": [[7, 12]]}}}
{"text": "用于车辆装卸危险化学品的围堰,防止泄漏和扩散", "label": {"keyword": {"装卸": [[4, 5]]}}}
{"text": "一种微型远红外气体浓度监测装置", "label": {"keyword": {"气体浓度监测": [[7, 12]]}}}
{"text": "手性N-肉桂基-N-苯基叔丁基亚磺酰胺及其制备和应用", "label": {"keyword": {"制备和应用": [[21, 25]]}}}
{"text": "具有偏振无关调制效率的低频电光相位调制器", "label": {"keyword": {"电光相位调制器": [[13, 19]], "偏振无关": [[2, 5]], "调制效率": [[6, 9]]}}}
{"text": "一种温和高效的纤维素分解制氢催化剂及其制备方法", "label": {"keyword": {"纤维素分解": [[7, 11]]}}}
{"text": "一种GIS设备现场冲击电压下局部放电测量装置", "label": {"keyword": {"放电测量": [[16, 19]]}}}
{"text": "一种海水淡化装置的试验台", "label": {"keyword": {"海水淡化": [[2, 5]]}}}
{"text": "一种新型梯级氨法脱硫脱硝塔", "label": {"keyword": {"氨法脱硫": [[6, 9]], "脱硫脱硝": [[8, 11]]}}}
{"text": "防倾翻保护装置及工程机械", "label": {"keyword": {"工程机械": [[8, 11]]}}}
{"text": "一种应用于自动化冲压生产线的可控脱模顶出装置", "label": {"keyword": {"冲压生产线": [[8, 12]]}}}
{"text": "一种温度检测自动给煤装置", "label": {"keyword": {"温度检测": [[2, 5]]}}}
{"text": "一种转轴表面裂纹在线检测系统及检测方法", "label": {"keyword": {"在线检测系统": [[8, 13]]}}}
{"text": "一种钻,抽,排一体化煤层卸压增渗装置及其使用方法", "label": {"keyword": {"煤层卸压": [[10, 13]], "增渗": [[14, 15]], "卸压增渗": [[12, 15]]}}}
{"text": "一种烃油脱硫催化剂及其应用方法", "label": {"keyword": {"脱硫催化剂": [[4, 8]]}}}
{"text": "永磁同步直驱电机转子结构", "label": {"keyword": {"永磁同步": [[0, 3]]}}}
{"text": "双电源相互切换自动切换装置", "label": {"keyword": {"自动切换装置": [[7, 12]]}}}
{"text": "一种用于电化学制备超小型热电偶的装置", "label": {"keyword": {"电化学制备": [[4, 8]]}}}
{"text": "一种季鏻盐水溶液的脱水方法", "label": {"keyword": {"季鏻": [[2, 3]], "季鏻盐": [[2, 4]], "季鏻盐": [[2, 4]]}}}
{"text": "一种相位-通用动脉双向绿波协调控制方法", "label": {"keyword": {"绿波协调": [[11, 14]], "绿波协调控制": [[11, 16]], "协调控制方法": [[13, 18]]}}}
{"text": "一种基于粒子群优化的跳频信号参数估计方法", "label": {"keyword": {"粒子群优化": [[4, 8]]}}}
{"text": "储氢合金吸放氢原位同步辐射X射线衍射试验装置", "label": {"keyword": {"储氢合金": [[0, 3]], "同步辐射": [[9, 12]], "储氢合金": [[0, 3]]}}}
{"text": "一种高效低能耗有机胺湿法烟气脱硫脱附系统", "label": {"keyword": {"低能耗": [[4, 6]], "湿法烟气脱硫": [[10, 15]], "烟气脱硫": [[12, 15]], "低能耗": [[4, 6]]}}}
{"text": "一种具有多模式切换系统的汽车自适应巡航系统及其控制方法", "label": {"keyword": {"自适应巡航系统": [[14, 20]]}}}
{"text": "一种钨酸铋-二氧化钛异质结复合光催化材料的制备方法", "label": {"keyword": {"光催化材料": [[15, 19]], "复合光催化材料": [[13, 19]]}}}
{"text": "椭圆曲线密码系统的双点系统", "label": {"keyword": {"椭圆曲线密码系统": [[0, 7]]}}}
{"text": "一种石墨烯改性反应装置", "label": {"keyword": {"石墨烯改性": [[2, 6]]}}}
{"text": "棉花酪氨酸蛋白磷酸酶GhPTP1及其编码基因及应用", "label": {"keyword": {"酪氨酸蛋白磷酸酶": [[2, 9]]}}}
{"text": "用于建造无开缝混凝土结构的模板加固系统", "label": {"keyword": {"模板加固": [[13, 16]]}}}
{"text": "一种发电系统零功率保护的方法和装置", "label": {"keyword": {"发电系统": [[2, 5]]}}}
{"text": "核电站反应堆保护系统的连接结构及连接方法", "label": {"keyword": {"反应堆保护系统": [[3, 9]], "反应堆保护系统": [[3, 9]]}}}
{"text": "一种检测盐酸克伦特罗的电化学修饰电极及检测装置", "label": {"keyword": {"化学修饰电极": [[12, 17]]}}}
{"text": "一种新型喹唑啉衍生物LU1503及其制备方法和应用", "label": {"keyword": {"方法和应用": [[20, 24]], "喹唑啉衍生物": [[4, 9]], "喹唑啉衍生物": [[4, 9]]}}}
{"text": "光波干涉场数字成像系统", "label": {"keyword": {"数字成像系统": [[5, 10]]}}}
{"text": "一种含有嵌套碳硼烷的有机金属化合物晶体及其制备方法", "label": {"keyword": {"有机金属化合物": [[10, 16]]}}}
{"text": "一种用于油气田开发的井口注入器", "label": {"keyword": {"气田开发": [[5, 8]], "油气田开发": [[4, 8]]}}}
{"text": "一种适用于高压输电网的电网故障诊断方法", "label": {"keyword": {"故障诊断方法": [[13, 18]]}}}
{"text": "具有二级对消功能的收发天线共址耦合干扰抑制装置", "label": {"keyword": {"干扰抑制": [[17, 20]]}}}
{"text": "X射线荧光光谱在线检测工业环境空气中重金属的方法", "label": {"keyword": {"荧光光谱": [[3, 6]]}}}
{"text": "智能监控吸风精密排种装置", "label": {"keyword": {"智能监控": [[0, 3]], "精密排种装置": [[6, 11]], "精密排种": [[6, 9]]}}}
{"text": "用于减少气泡干扰的附加挡板和科学研究容器", "label": {"keyword": {"和科学研究": [[13, 17]]}}}
{"text": "一种石墨电子散热材料及其制备方法和应用", "label": {"keyword": {"电子散热": [[4, 7]]}}}
{"text": "一种N-烷(酰基)取代氨基香豆素及其杀虫活性", "label": {"keyword": {"杀虫活性": [[18, 21]]}}}
{"text": "一种用于功率LED封装的苯基含氢硅油的制备方法", "label": {"keyword": {"含氢硅油": [[14, 17]]}}}
{"text": "茶叶中有效成分的综合制备技术", "label": {"keyword": {"制备技术": [[10, 13]]}}}
{"text": "一种基于合成孔径声纳图像的水体区域检测方法及系统", "label": {"keyword": {"合成孔径声纳": [[4, 9]]}}}
{"text": "一种高透湿水性聚氨酯材料及其制备方法", "label": {"keyword": {"聚氨酯材料": [[7, 11]], "水性聚氨酯": [[5, 9]]}}}
{"text": "一种集中捕获磁选装置及其分离方法", "label": {"keyword": {"磁选装置": [[6, 9]]}}}
{"text": "一种高结构强度铝合金轮毂的制备方法", "label": {"keyword": {"铝合金轮毂": [[7, 11]]}}}
{"text": "城市生活垃圾生物质环保可再生能源干燥系统", "label": {"keyword": {"环保": [[9, 10]]}}}
{"text": "一种基于主动降噪的风机主动降噪系统", "label": {"keyword": {"降噪系统": [[13, 16]]}}}
{"text": "一种用于真空环境的电绝缘管支撑组件", "label": {"keyword": {"电绝缘": [[9, 11]]}}}
{"text": "一种抗屈曲支撑自平衡垂直加载试验系统及方法", "label": {"keyword": {"抗屈曲支撑": [[2, 6]]}}}
{"text": "一种反硝化菌试瓶的生产方法", "label": {"keyword": {"反硝化菌": [[2, 5]]}}}
{"text": "基于流体动力学的全光纤高压脉冲电场传感器及传感系统", "label": {"keyword": {"高压脉冲电场": [[11, 16]], "电场传感器": [[15, 19]], "脉冲电场": [[13, 16]]}}}
{"text": "用于化学测量的多自适应活套", "label": {"keyword": {"化学测量": [[2, 5]]}}}
{"text": "一种用于快速分析和鉴定小麦外源染色体的多色荧光原位杂交方法", "label": {"keyword": {"多色荧光": [[19, 22]], "多色荧光原位杂交": [[19, 26]], "原位杂交": [[23, 26]], "荧光原位杂交": [[21, 26]]}}}
{"text": "数据库综合监管平台及其工作方法及基于该平台的备份任务流程管理业务控制方法", "label": {"keyword": {"综合监管": [[3, 6]]}}}
{"text": "俯仰三旋翼无人机姿态高度自适应鲁棒控制方法", "label": {"keyword": {"鲁棒控制方法": [[15, 20]], "无人机": [[5, 7]], "自适应鲁棒控制": [[12, 18]]}}}
{"text": "一种可逆物理交联剂及其制备方法", "label": {"keyword": {"物理交联": [[4, 7]], "物理交联": [[4, 7]]}}}
{"text": "开关柜保护测控装置操作手柄遥控装置及方法", "label": {"keyword": {"测控": [[5, 6]]}}}
{"text": "一种利用遥感数字图像和数字地形图获取水平地面自然光散射/直接光照比的方法", "label": {"keyword": {"数字地形图": [[11, 15]]}}}
{"text": "煤制油加氢反应器用厚壁管型钢锻件的制造方法", "label": {"keyword": {"加氢反应器": [[3, 7]]}}}
{"text": "非晶变压器线圈压力整形台车", "label": {"keyword": {"非晶变压器": [[0, 4]]}}}
{"text": "杂波环境下基于收发联合优化的自适应滤波方法", "label": {"keyword": {"自适应滤波方法": [[14, 20]]}}}
{"text": "差分共焦内聚焦法透镜光轴和厚度测量方法及装置", "label": {"keyword": {"厚度测量": [[13, 16]], "差分共焦": [[0, 3]]}}}
{"text": "一种催化裂化汽油吸附脱硫工艺", "label": {"keyword": {"吸附脱硫": [[8, 11]], "脱硫工艺": [[10, 13]], "催化裂化汽油": [[2, 7]]}}}
{"text": "一种带通讯功能的电磁阀遥控器", "label": {"keyword": {"通讯功能": [[3, 6]]}}}
{"text": "半导体照明用近紫外激发蓝橙色荧光粉及其制备方法", "label": {"keyword": {"半导体照明": [[0, 4]]}}}
{"text": "一种CAN通讯丢失故障诊断方法及电控单元", "label": {"keyword": {"故障诊断方法": [[9, 14]], "电控单元": [[16, 19]]}}}
{"text": "一种汽油选择性加氢脱硫本体催化剂及其制备方法和应用", "label": {"keyword": {"选择性加氢脱硫": [[4, 10]]}}}
{"text": "插入式下降管座角焊缝超声相控阵检测模拟试块", "label": {"keyword": {"相控阵检测": [[12, 16]]}}}
{"text": "一种用于低速风洞地面效应试验的可折叠上层装置", "label": {"keyword": {"低速风洞": [[4, 7]]}}}
{"text": "基于STM32单片机的双目测距系统", "label": {"keyword": {"单片机": [[7, 9]], "单片机": [[7, 9]]}}}
{"text": "一种压控脉冲分步恒流充电方法", "label": {"keyword": {"恒流充电": [[8, 11]]}}}
{"text": "一种落球法粘度系数测量仪的导管装置", "label": {"keyword": {"粘度系数": [[5, 8]]}}}
{"text": "一种抑制烟曲霉活性的新化合物及其制备方法和应用", "label": {"keyword": {"方法和应用": [[18, 22]]}}}
{"text": "供水企业三位一体的水质风险预警系统", "label": {"keyword": {"供水企业": [[0, 3]], "供水企业": [[0, 3]], "风险预警系统": [[11, 16]]}}}
{"text": "一种手持式单通道三路水面光谱自动测量装置及方法", "label": {"keyword": {"自动测量": [[14, 17]]}}}
{"text": "一种间接测量大型铸件铸造过程中表面温度变化的方法", "label": {"keyword": {"表面温度变化": [[15, 20]]}}}
{"text": "一种用于深度脱水的金属盐改性分子筛型吸附剂及制备方法", "label": {"keyword": {"改性分子筛": [[12, 16]]}}}
{"text": "一种鉴定黄鳍鲷的分子生物学方法", "label": {"keyword": {"分子生物学方法": [[8, 14]]}}}
{"text": "一种六方氮化硼空心微球的制备方法", "label": {"keyword": {"六方氮化硼": [[2, 6]]}}}
{"text": "一种铅锌浮选尾矿废水处理剂", "label": {"keyword": {"水处理剂": [[9, 12]]}}}
{"text": "一种埃坡霉素B的发酵生产工艺", "label": {"keyword": {"发酵生产": [[8, 11]]}}}
{"text": "波分复用系统中客户网保护倒换的协调控制装置及方法", "label": {"keyword": {"波分复用": [[0, 3]]}}}
{"text": "便于夜间施工的绝缘拉杆", "label": {"keyword": {"夜间施工": [[2, 5]]}}}
{"text": "一种三维多孔石墨烯负载碳包覆硫化锂正极材料及其制备方法和应用", "label": {"keyword": {"三维多孔": [[2, 5]], "正极材料": [[17, 20]], "三维多孔石墨烯": [[2, 8]]}}}
{"text": "一种滚茶接种发酵处理装置", "label": {"keyword": {"接种发酵": [[4, 7]], "发酵处理": [[6, 9]]}}}
{"text": "一种生物炭种类的分析鉴定方法", "label": {"keyword": {"分析鉴定": [[8, 11]]}}}
{"text": "一种考虑多目标的车辆自适应巡航控制方法", "label": {"keyword": {"自适应巡航控制": [[10, 16]]}}}
{"text": "高压细水雾灭火多功能电动洒水车", "label": {"keyword": {"高压细水雾": [[0, 4]], "高压细水雾": [[0, 4]]}}}
{"text": "一种光学谐振腔全反射镜自动调整机构", "label": {"keyword": {"光学谐振腔": [[2, 6]], "全反射镜": [[7, 10]]}}}
{"text": "一种风电塔筒安全监控系统", "label": {"keyword": {"安全监控系统": [[6, 11]]}}}
{"text": "基于一维半导体纳米材料的光电颜色传感器及其制备方法", "label": {"keyword": {"半导体纳米材料": [[4, 10]]}}}
{"text": "CO 的一种盲 ICI 相位噪声补偿方法？？大线宽OFDM系统", "label": {"keyword": {" 相位噪声补偿": [[11, 17]]}}}
{"text": "一种基于离子注入表面改性提高TC4钛合金抗气蚀性的方法", "label": {"keyword": {"抗气蚀": [[20, 22]]}}}
{"text": "一种往复式压缩机故障诊断装置", "label": {"keyword": {"往复式压缩机": [[2, 7]], "往复式压缩机": [[2, 7]]}}}
{"text": "一种发动机高压涡轮转子叶尖外径辅助测量装置", "label": {"keyword": {"高压涡轮": [[5, 8]]}}}
{"text": "一种3D地震结构曲率性能优化方法", "label": {"keyword": {"性能优化": [[10, 13]]}}}
{"text": "超声波-光催化耦合果蔬清洗装置", "label": {"keyword": {"果蔬": [[9, 10]]}}}
{"text": "一种用于有机废气处理的光催化组件", "label": {"keyword": {"有机废气处理": [[4, 9]]}}}
{"text": "一种固定源低烟尘浓度烟气细颗粒物取样装置", "label": {"keyword": {"细颗粒物": [[12, 15]]}}}
{"text": "一种水萃取法和超临界CO 2萃取法得到的复合烟草香气物质的再造烟叶及其制备的卷烟", "label": {"keyword": {"再造烟叶": [[29, 32]], "再造烟叶": [[29, 32]], "再造烟叶": [[29, 32]]}}}
{"text": "一种具有降糖降脂活性的无环1,3-二羰基PPAR双活化化合物及其制备方法", "label": {"keyword": {"降糖降脂": [[4, 7]]}}}
{"text": "液化天然气接收站蒸发气直接输出工艺及装置", "label": {"keyword": {"液化天然气": [[0, 4]]}}}
{"text": "电力设备专业维修基地维修数据处理系统", "label": {"keyword": {"电力设备": [[0, 3]], "数据处理系统": [[12, 17]]}}}
{"text": "一种纳米压电免疫传感器的制备方法及其应用", "label": {"keyword": {"压电免疫传感器": [[4, 10]]}}}
{"text": "风电系统储能电能质量调节器", "label": {"keyword": {"电能质量调节器": [[6, 12]]}}}
{"text": "YNd1接线变压器纵向差动保护电流相位补偿方法", "label": {"keyword": {"纵向差动保护": [[9, 14]], "差动保护": [[11, 14]]}}}
{"text": "一种复合填料层自养反硝化微生物系统同时去除总氮和消炎药的方法", "label": {"keyword": {"消炎药": [[24, 26]], "自养反硝化": [[7, 11]], "消炎药": [[24, 26]]}}}
{"text": "大倾角特厚煤层短壁放顶煤工作面放煤控制系统", "label": {"keyword": {"特厚煤层": [[3, 6]], "顶煤工作面": [[10, 14]]}}}
{"text": "含油致密砂岩孔径分布特征的测量方法", "label": {"keyword": {"分布特征": [[8, 11]]}}}
{"text": "基于CA-PSO混合优化算法的多态车间布局优化方法", "label": {"keyword": {"优化算法": [[10, 13]]}}}
{"text": "一种垂直交换耦合场大小可调的复合磁性多层结构", "label": {"keyword": {"交换耦合场": [[4, 8]]}}}
{"text": "壳聚糖降解复合酶制剂及其制备方法", "label": {"keyword": {"复合酶制剂": [[5, 9]]}}}
{"text": "基于乙炔气体吸收峰的DFB激光器波长解调方法及系统", "label": {"keyword": {"波长解调": [[16, 19]]}}}
{"text": "用于血清肿瘤标志物检测的巨磁阻抗效应生物传感器", "label": {"keyword": {"巨磁阻抗": [[12, 15]], "巨磁阻抗效应": [[12, 17]]}}}
{"text": "基于电流逆变器的光伏/电池混合分布式发电系统", "label": {"keyword": {"分布式发电系统": [[15, 21]], "分布式发电": [[15, 19]], "发电系统": [[18, 21]], "混合分布式发电": [[13, 19]], "分布式发电": [[15, 19]]}}}
{"text": "室外真空断路器进出线套管连接装置及室外真空断路器", "label": {"keyword": {"真空断路器": [[2, 6], [19, 23]]}}}
{"text": "高炉炉顶分配器齿轮箱倾动机构无线测温系统", "label": {"keyword": {"测温系统": [[16, 19]]}}}
{"text": "一种提高高强度铝合金焊接接头耐腐蚀性能的方法", "label": {"keyword": {"铝合金焊接接头": [[7, 13]], "高强度铝合金": [[4, 9]]}}}
{"text": "发电机水灭火自动控制系统", "label": {"keyword": {"自动控制系统": [[6, 11]]}}}
{"text": "五环三萜在制备糖原磷酸化酶抑制剂中的应用", "label": {"keyword": {"糖原磷酸化酶抑制剂": [[7, 15]], "糖原磷酸化酶抑制剂": [[7, 15]], "糖原磷酸化酶": [[7, 12]]}}}
{"text": "一种制备双金属向心推力滑动轴承毛坯的装置及其制备方法", "label": {"keyword": {"推力滑动轴承": [[9, 14]]}}}
{"text": "中红外光谱预测脱硫胺溶液中硫化氢含量的方法", "label": {"keyword": {"中红外光谱": [[0, 4]], "中红外光谱": [[0, 4]], "红外光谱": [[1, 4]]}}}
{"text": "负性聚酰亚胺感光材料及其制备方法", "label": {"keyword": {"感光材料": [[6, 9]]}}}
{"text": "一种硫酸头孢喹诺的肺靶向PLGA微球制剂及其制备方法", "label": {"keyword": {"微球制剂": [[16, 19]]}}}
{"text": "一种废气净化处理的储存装置", "label": {"keyword": {"废气净化": [[2, 5]], "净化处理": [[4, 7]]}}}
{"text": "真空感应熔炼炉热电偶组件", "label": {"keyword": {"真空感应熔炼": [[0, 5]]}}}
{"text": "一种电能表,集中抄表,负控端一体化调试装置", "label": {"keyword": {"电能表": [[2, 4]]}}}
{"text": "一种供电系统远程监控系统", "label": {"keyword": {"远程监控系统": [[6, 11]]}}}
{"text": "一种基于内模控制的电力设备有源噪声抑制方法", "label": {"keyword": {"噪声抑制方法": [[15, 20]]}}}
{"text": "一种化学链燃烧氧载体的批量制备方法及装置", "label": {"keyword": {"化学链燃烧": [[2, 6]]}}}
{"text": "一种具有活细胞发育功能的锰络合物双光子吸收材料及其合成方法", "label": {"keyword": {"双光子吸收": [[16, 20]]}}}
{"text": "一种潜在指纹提取/显示凝胶复合膜及其辐射制备方法", "label": {"keyword": {"指纹提取": [[4, 7]]}}}
{"text": "头孢克肟晶体,其制备方法和含有该晶体的片剂组合物", "label": {"keyword": {"含有": [[13, 14]]}}}
{"text": "一种应用于电气自动化的种子计数机", "label": {"keyword": {"电气自动化": [[5, 9]]}}}
{"text": "生产物流条码数据采集与控制系统", "label": {"keyword": {"数据采集与控制": [[6, 12]], "数据采集与控制系统": [[6, 14]], "采集与控制": [[8, 12]]}}}
{"text": "利用碱土金属减少杂质掺入 III-氮化物晶体", "label": {"keyword": {"碱土金属": [[2, 5]], "杂质掺入": [[8, 11]]}}}
{"text": "基于手机定位和移动轨迹的楼梯上下分流方法", "label": {"keyword": {"手机定位": [[2, 5]]}}}
{"text": "一种电感耦合等离子体质谱检测乙型肝炎表面抗原的方法", "label": {"keyword": {"电感耦合等离子体": [[2, 9]], "电感耦合等离子体质谱": [[2, 11]]}}}
{"text": "基于STM8单片机的小型恒温电烙铁控制电路", "label": {"keyword": {"单片机": [[6, 8]]}}}
{"text": "内含子衍生环状RNA分子及其关键核酸序列在环形成中的应用", "label": {"keyword": {"核酸序列": [[16, 19]]}}}
{"text": "磁性粒子与量子点核壳纳米复合粒子的制备方法", "label": {"keyword": {"纳米复合粒子": [[10, 15]], "纳米复合粒子": [[10, 15]]}}}
{"text": "一种基于人机交互的电影观众体验评价方法", "label": {"keyword": {"人机交互": [[4, 7]]}}}
{"text": "Ag 2 Se 量子点染料共敏化太阳能电池的制备方法", "label": {"keyword": {"敏化太阳能电池": [[14, 20]]}}}
{"text": "一种钢管水浸法超声波探伤装置及其检测盆", "label": {"keyword": {"超声波探伤": [[7, 11]], "水浸法": [[4, 6]]}}}
{"text": "电泳输送系统导轨的制作安装方法及辅助安装装置", "label": {"keyword": {"辅助安装": [[16, 19]]}}}
{"text": "频率采样耦合干扰解决电路", "label": {"keyword": {"耦合干扰": [[4, 7]]}}}
{"text": "一种含碳耐火材料的粘合剂", "label": {"keyword": {"含碳耐火材料": [[2, 7]]}}}
{"text": "一种长距离矿井通风系统", "label": {"keyword": {"矿井通风系统": [[5, 10]]}}}
{"text": "一种城市公共交通动态调度优化方法及系统", "label": {"keyword": {"调度优化": [[10, 13]]}}}
{"text": "焊缝跟踪检测设备及方法", "label": {"keyword": {"焊缝跟踪": [[0, 3]]}}}
{"text": "一种具有自传感功能的滚珠丝杠副预紧力测控系统及方法", "label": {"keyword": {"测控系统": [[18, 21]], "测控": [[18, 19]]}}}
{"text": "用于 3D 打印的热敏培养表面复合材料", "label": {"keyword": {"表面复合材料": [[13, 18]]}}}
{"text": "一种高阈值电压和高迁移率的凹栅 MOSFET 结构", "label": {"keyword": {"高阈值电压": [[2, 6]]}}}
{"text": "一种通用电磁信号自动搜索方法", "label": {"keyword": {"自动搜索方法": [[8, 13]]}}}
{"text": "基于BIM的建筑工程管理系统", "label": {"keyword": {"建筑工程管理": [[6, 11]], "工程管理": [[8, 11]], "建筑工程": [[6, 9]]}}}
{"text": "一种用双锥压头测量材料力学性能的方法", "label": {"keyword": {"材料力学性能": [[9, 14]]}}}
{"text": "一种高温用低剩磁温度系数钐钴永磁材料及制备方法", "label": {"keyword": {"温度系数": [[8, 11]]}}}
{"text": "超长单晶V 2 O 5纳米线/石墨烯正极材料及制备方法", "label": {"keyword": {"正极材料": [[18, 21]]}}}
{"text": "一种检测高压电缆分路导体交流电阻的装置", "label": {"keyword": {"交流电阻": [[12, 15]]}}}
{"text": "动态结晶制备纳米沸石金属有机骨架化合物晶体的方法", "label": {"keyword": {"动态结晶": [[0, 3]], "金属有机骨架化合物": [[10, 18]], "金属有机骨架": [[10, 15]]}}}
{"text": "一种基于单级行星齿轮传动的差动变压器方向盘角度传感器", "label": {"keyword": {"行星齿轮传动": [[6, 11]], "差动变压器": [[13, 17]]}}}
{"text": "杯4芳烃衍生物液膜载体铅离子液膜转运装置及方法", "label": {"keyword": {"液膜转运": [[14, 17]], "杯4芳烃衍生物": [[0, 6]]}}}
{"text": "高压发电机变压器油纸绝缘测试系统", "label": {"keyword": {"变压器油纸绝缘": [[5, 11]]}}}
{"text": "双光束激光质谱法原位检测动物组织中的药物分子", "label": {"keyword": {"激光质谱": [[3, 6]]}}}
{"text": "一种城市配网屏风柜防凝露装置", "label": {"keyword": {"城市配网": [[2, 5]]}}}
{"text": "一种基于氧化石墨烯膜电渗析空气直接除湿的控制装置", "label": {"keyword": {"氧化石墨烯膜": [[4, 9]]}}}
{"text": "二氧化钛废酸处理城市污泥的后污泥减量法", "label": {"keyword": {"二氧化钛废酸": [[0, 5]]}}}
{"text": "三路压电驱动的二维平行精密定位机构", "label": {"keyword": {"定位机构": [[13, 16]], "精密定位": [[11, 14]]}}}
{"text": "一种油田加热炉烟气脱硫除尘装置", "label": {"keyword": {"烟气脱硫": [[7, 10]], "油田加热炉": [[2, 6]], "脱硫除尘": [[9, 12]]}}}
{"text": "220kV线路多回双分裂导体绝缘子带电更换工具", "label": {"keyword": {"双分裂导体": [[9, 13]]}}}
{"text": "一种大豆组织蛋白即食营养风味食品", "label": {"keyword": {"大豆组织蛋白": [[2, 7]]}}}
{"text": "轴流风扇,便于振动测量", "label": {"keyword": {"振动测量": [[7, 10]]}}}
{"text": "分子标记,染色体消失法结合轮回选择法在小麦多基因聚集育种中的应用", "label": {"keyword": {"染色体消失": [[5, 9]]}}}
{"text": "阳离子纸张增强剂及其制备和使用方法", "label": {"keyword": {"纸张增强剂": [[3, 7]]}}}
{"text": "柜式空调出风口屏蔽装置及其控制方法", "label": {"keyword": {"柜式空调": [[0, 3]]}}}
{"text": "一种对称布局多旋翼无人机动力中心位置检测方法", "label": {"keyword": {"无人机": [[9, 11]], "多旋翼无人机": [[6, 11]]}}}
{"text": "丛枝菌根真菌诱导启动子及其应用", "label": {"keyword": {"丛枝菌根真菌": [[0, 5]]}}}
{"text": "堆叠纳米线MOS晶体管及其制造方法", "label": {"keyword": {"其制造方法": [[12, 16]]}}}
{"text": "荔枝异粒变速控释肥及其制备方法", "label": {"keyword": {"控释肥": [[6, 8]]}}}
{"text": "利用低温电流带走热量的新型金属散热方式", "label": {"keyword": {"散热方式": [[15, 18]]}}}
{"text": "基于表面等离子体增强透射的双盘纳米天线金属复合微纳结构", "label": {"keyword": {"增强透射": [[8, 11]]}}}
{"text": "植物中转基因蛋白CP4-EPSPS的定量检测方法", "label": {"keyword": {"定量检测": [[18, 21]]}}}
{"text": "一种基站环境电磁辐射估计方法及装置", "label": {"keyword": {"电磁辐射": [[6, 9]]}}}
{"text": "一种静压润滑推力轴承的动态压力补偿机构", "label": {"keyword": {"压力补偿": [[13, 16]]}}}
{"text": "一种气固两相流参数测量装置", "label": {"keyword": {"气固两相流": [[2, 6]], "参数测量": [[7, 10]]}}}
{"text": "一种吸附甲基橙染料的氧化石墨烯/羧甲基壳聚糖磁性微球吸附剂及其制备方法", "label": {"keyword": {"羧甲基壳聚糖": [[16, 21]]}}}
{"text": "一种微光视频图像增强方法", "label": {"keyword": {"图像增强方法": [[6, 11]]}}}
{"text": "一种石墨烯的电化学制备方法", "label": {"keyword": {"电化学制备": [[6, 10]], "化学制备方法": [[7, 12]]}}}
{"text": "一种旋转机械主轴的减振装置", "label": {"keyword": {"减振装置": [[9, 12]]}}}
{"text": "一种通过聚焦强磁场干预复杂晶体生长的研究装置", "label": {"keyword": {"强磁场": [[6, 8]]}}}
{"text": "一种用于机械制造的圆管快速磨床", "label": {"keyword": {"机械制造": [[4, 7]], "机械制造": [[4, 7]], "机械制造": [[4, 7]]}}}
{"text": "基于石墨烯电吸收特性的微环光开关", "label": {"keyword": {"吸收特性": [[6, 9]], "吸收特性": [[6, 9]], "吸收特性": [[6, 9]]}}}
{"text": "烟草用安息香香提取物的制备方法及应用", "label": {"keyword": {"方法及应用": [[13, 17]]}}}
{"text": "一种便于移动的立式柜式空调支架底座", "label": {"keyword": {"柜式空调": [[9, 12]]}}}
{"text": "一种具有抗氧化和抗肿瘤活性的海带多糖及其提取分离方法", "label": {"keyword": {"抗肿瘤活性": [[8, 12]], "提取分离": [[20, 23]]}}}
{"text": "一种摩擦实验中实时观察磨痕形态的装置", "label": {"keyword": {"实时观察": [[7, 10]]}}}
{"text": "提高电熔镁块结晶质量的数值模拟方法", "label": {"keyword": {"数值模拟方法": [[11, 16]]}}}
{"text": "一种可调节的多面油刷,用于刷洗再生混凝土砌块模具", "label": {"keyword": {"再生混凝土砌块": [[15, 21]]}}}
{"text": "一种混沌粒子群优化算法", "label": {"keyword": {"优化算法": [[7, 10]]}}}
{"text": "基于Omega形状特征的人体目标检测方法", "label": {"keyword": {"目标检测方法": [[14, 19]]}}}
{"text": "球保持架式等速传动轴总成圆周间隙检测方法", "label": {"keyword": {"圆周间隙": [[12, 15]]}}}
{"text": "一种用于汽车自动变速器的一体式组合电磁阀", "label": {"keyword": {"自动变速器": [[6, 10]], "自动变速器": [[6, 10]]}}}
{"text": "一种布局紧凑的外腔反馈二极管激光光谱合成光学系统", "label": {"keyword": {"外腔反馈": [[7, 10]]}}}
{"text": "一种机载雷达集成天线实时变形测量系统及方法", "label": {"keyword": {"实时变形": [[10, 13]]}}}
{"text": "一种太阳能发电循环冷却系统及其控制方法", "label": {"keyword": {"循环冷却系统": [[7, 12]]}}}
{"text": "一种大豆根瘤内生菌DEnt1302及其制备方法和应用,菌剂及其制备方法", "label": {"keyword": {"方法和应用": [[21, 25]]}}}
{"text": "基于车贴技术的低速风洞双锯齿固定过渡带", "label": {"keyword": {"低速风洞": [[7, 10]]}}}
{"text": "光刻胶-石墨烯量子点发光复合体系的制备方法", "label": {"keyword": {"石墨烯量子点": [[4, 9]]}}}
{"text": "煤层二氧化碳注入测试渗透装置", "label": {"keyword": {"二氧化碳注入": [[2, 7]]}}}
{"text": "光电电流互感器故障检测装置", "label": {"keyword": {"故障检测装置": [[7, 12]]}}}
{"text": "一种利用磁化率检测石英砂中铁含量的方法", "label": {"keyword": {"磁化率": [[4, 6]]}}}
{"text": "棉织物香精微胶囊复合有机硅柔软剂的制备方法及应用", "label": {"keyword": {"香精微胶囊": [[3, 7]]}}}
{"text": "聚苯胺-碳层-氮化钛纳米线阵列复合材料及其制备方法和应用", "label": {"keyword": {"氮化钛纳米线": [[7, 12]]}}}
{"text": "肝干细胞长期体外培养和定向分化的系统和方法", "label": {"keyword": {"定向分化": [[11, 14]], "定向分化": [[11, 14]]}}}
{"text": "防爆自控防喷电加热装置", "label": {"keyword": {"电加热装置": [[6, 10]]}}}
{"text": "大型电站综合自动化系统仿真平台", "label": {"keyword": {"综合自动化系统": [[4, 10]], "综合自动化系统": [[4, 10]], "综合自动化": [[4, 8]], "综合自动化": [[4, 8]]}}}
{"text": "一种邻苯二甲酸氢钾单晶生长支架", "label": {"keyword": {"单晶生长": [[9, 12]], "邻苯二甲酸氢钾": [[2, 8]]}}}
{"text": "基于沸石载体的加氢脱硫催化剂的制备方法", "label": {"keyword": {"加氢脱硫催化剂": [[7, 13]], "脱硫催化剂": [[9, 13]], "加氢脱硫催化剂": [[7, 13]]}}}
{"text": "数字化高频谐振软开关电路电流跟踪同步方法及装置", "label": {"keyword": {"跟踪同步": [[14, 17]]}}}
{"text": "一种三4-(4-吗啉基)-1,8-萘酰亚胺乙基胺荧光试剂及其制备和应用", "label": {"keyword": {"制备和应用": [[30, 34]]}}}
{"text": "一种节水型生活污水处理系统", "label": {"keyword": {"生活污水处理": [[5, 10]], "污水处理系统": [[7, 12]]}}}
{"text": "工程翻新轮胎多层复合层试验模型", "label": {"keyword": {"多层复合": [[6, 9]]}}}
{"text": "带宽预留参数配置方法及装置", "label": {"keyword": {"带宽预留": [[0, 3]]}}}
{"text": "一种筛选干细胞因子受体激酶抑制剂的高通量筛选方法", "label": {"keyword": {"高通量筛选": [[17, 21]], "干细胞因子受体": [[4, 10]], "高通量筛选": [[17, 21]]}}}
{"text": "用于乙烯聚合或共聚的催化剂组分及其催化剂", "label": {"keyword": {"乙烯聚合": [[2, 5]], "乙烯聚合": [[2, 5]]}}}
{"text": "一种无人值守变电站门控管理方法", "label": {"keyword": {"无人值守变电站": [[2, 8]]}}}
{"text": "一种镍铈催化剂及其制备方法和应用", "label": {"keyword": {"方法和应用": [[11, 15]]}}}
{"text": "一种树苔发酵提取物及其制备方法和应用", "label": {"keyword": {"方法和应用": [[13, 17]]}}}
{"text": "一种珍珠蛋白的制备方法,由该方法制备的珍珠蛋白及其应用", "label": {"keyword": {"及其应用": [[23, 26]]}}}
{"text": "一种多晶硅隔膜结构的制造方法", "label": {"keyword": {"多晶硅": [[2, 4]]}}}
{"text": "一种环保型双金属钙钛矿量子点的制备方法", "label": {"keyword": {"钙钛矿量子点": [[8, 13]], "钙钛矿量子点": [[8, 13]]}}}
{"text": "具有人造磁导体反射器的抗金属RFID标签天线", "label": {"keyword": {"人造磁导体": [[2, 6]]}}}
{"text": "一种提高牛肉多不饱和脂肪酸含量的饲料", "label": {"keyword": {"饱和脂肪酸": [[8, 12]], "不饱和脂肪酸": [[7, 12]], "不饱和脂肪酸": [[7, 12]], "多不饱和脂肪酸": [[6, 12]], "多不饱和脂肪酸": [[6, 12]]}}}
{"text": "一种耐盐驱油剂及其应用", "label": {"keyword": {"及其应用": [[7, 10]]}}}
{"text": "基于线宽测量的智能快速成型流程控制方法", "label": {"keyword": {"线宽测量": [[2, 5]]}}}
{"text": "连杆开裂槽激光加工夹具装置", "label": {"keyword": {"连杆开裂": [[0, 3]]}}}
{"text": "一种用作电池负极的镁合金片及其制备方法", "label": {"keyword": {"镁合金片": [[9, 12]]}}}
{"text": "一种用于飞机机身对接总成的环形数控自动打孔系统", "label": {"keyword": {"自动打孔": [[17, 20]]}}}
{"text": "一种基于人工智能的配电线路跳闸报告质量评价方法", "label": {"keyword": {"人工智能": [[4, 7]]}}}
{"text": "基于四极射频电场增强的真空紫外光电离和化学电离复合电离源", "label": {"keyword": {"电场增强": [[6, 9]], "真空紫外光": [[11, 15]]}}}
{"text": "一种利用沼渣制备镉污染场地高效生态修复菌群的方法", "label": {"keyword": {"生态修复": [[15, 18]]}}}
{"text": "三相永磁同步电机相序检测及转子初始位置定位系统及方法", "label": {"keyword": {"相序检测": [[8, 11]]}}}
{"text": "基于二次电子倍增的自稳电流微脉冲电子枪", "label": {"keyword": {"二次电子倍增": [[2, 7]], "电子倍增": [[4, 7]]}}}
{"text": "双八羟基喹啉铝络合物及其在2,4,6-三硝基苯酚检测中的应用", "label": {"keyword": {"八羟基喹啉铝": [[1, 6]], "羟基喹啉铝": [[2, 6]]}}}
{"text": "永磁同步电机转子位置PI控制参数的调整方法", "label": {"keyword": {"永磁同步电机": [[0, 5]]}}}
{"text": "温差作业设备自动防冻装置", "label": {"keyword": {"温差": [[0, 1]]}}}
{"text": "一种氮掺杂荧光石墨烯量子点及其制备方法", "label": {"keyword": {"石墨烯量子点": [[7, 12]]}}}
{"text": "基于AT89C51单片机的空气净化器", "label": {"keyword": {"单片机": [[9, 11]], "51单片机": [[7, 11]]}}}
{"text": "奥氏体不锈钢管中氧化物的磁性无损检测方法及装置", "label": {"keyword": {"奥氏体不锈钢": [[0, 5]], "奥氏体不锈钢管": [[0, 6]], "无损检测": [[14, 17]], "无损检测": [[14, 17]], "无损检测方法": [[14, 19]]}}}
{"text": "一种利用碱化乳状磷脂生产粉状磷脂的方法", "label": {"keyword": {"粉状磷脂": [[12, 15]]}}}
{"text": "载碳流化床催化剂的出料方法", "label": {"keyword": {"流化床催化剂": [[2, 7]]}}}
{"text": "一种圆柱永磁同步直线电机推力优化设计方法", "label": {"keyword": {"圆柱永磁同步直线电机": [[2, 11]]}}}
{"text": "用于 60GHz 无线通信的 1:1 结构 27MHz 晶体频率合成器", "label": {"keyword": {"频率合成器": [[30, 34]]}}}
{"text": "纤维表面处理剂,其制备方法和使用方法,压裂液用纤维", "label": {"keyword": {"表面处理剂": [[2, 6]], "纤维表面处理": [[0, 5]]}}}
{"text": "基于球面复用双异质结量子点的人工复眼激光系统", "label": {"keyword": {"人工复眼": [[14, 17]]}}}
{"text": "电力抢修综合检测部署系统", "label": {"keyword": {"综合检测": [[4, 7]]}}}
{"text": "异形断面双层铝合金空间网格结构", "label": {"keyword": {"空间网格结构": [[9, 14]]}}}
{"text": "一种甲烷制乙烯和合成气双功能催化剂的制备方法", "label": {"keyword": {"双功能催化剂": [[11, 16]]}}}
{"text": "微流控通道表面微流控芯片接枝聚电解质刷抑制电渗流", "label": {"keyword": {"聚电解质刷": [[14, 18]]}}}
{"text": "负压供水气压调节自动控制系统", "label": {"keyword": {"自动控制系统": [[8, 13]], "负压供水": [[0, 3]]}}}
{"text": "一种基于遗传算法优化的多态性检测器生成方法", "label": {"keyword": {"遗传算法优化": [[4, 9]]}}}
{"text": "一种2？？羰？？ 2??苯乙酸对叔丁基苯甲酰腙二苯基锡络合物及其制备方法和应用", "label": {"keyword": {"方法和应用": [[34, 38]]}}}
{"text": "汽轮机转子安全风险在线监控装置及方法", "label": {"keyword": {"监控": [[11, 12]]}}}
{"text": "基于ARIMA和LSSVM模型的CPI组合预测方法", "label": {"keyword": {"组合预测方法": [[19, 24]]}}}
{"text": "一种具有快速吸液止血性能的海藻酸盐复合水凝胶及其制备方法", "label": {"keyword": {"止血性能": [[8, 11]]}}}
{"text": "一种用于受激发射损耗显微镜的全保偏光纤激光晶格发生器", "label": {"keyword": {"保偏光纤": [[15, 18]], "保偏": [[15, 16]], "受激发射损耗显微镜": [[4, 12]], "受激发射损耗": [[4, 9]]}}}
{"text": "一种高温高压阀门复合启闭装置", "label": {"keyword": {"启闭装置": [[10, 13]], "高温高压": [[2, 5]]}}}
{"text": "变风速下风力发电系统最大功率点跟踪方法", "label": {"keyword": {"风力发电": [[4, 7]]}}}
{"text": "一种手性三元碳环嘧啶核苷类似物及其制备方法", "label": {"keyword": {"嘧啶核苷": [[8, 11]]}}}
{"text": "复合匹配铜缓蚀剂的制备及表面处理方法", "label": {"keyword": {"表面处理方法": [[12, 17]]}}}
{"text": "一种压送式高压密相气力输送装置及气力输送方法", "label": {"keyword": {"密相气力输送": [[7, 12]]}}}
{"text": "IEC61850智能变电站IED工况远程诊断系统", "label": {"keyword": {"远程诊断系统": [[18, 23]], "智能变电站": [[8, 12]]}}}
{"text": "一种石斑鱼精子超低温保存方法", "label": {"keyword": {"超低温": [[7, 9]], "低温保存": [[8, 11]]}}}
{"text": "掩模电化学加工的恒力机构", "label": {"keyword": {"恒力机构": [[8, 11]]}}}
{"text": "一种城市固体废物处理系统", "label": {"keyword": {"固体废物处理": [[4, 9]], "城市固体废物": [[2, 7]], "城市固体废物处理": [[2, 9]]}}}
{"text": "一种防止钢卷外圈划伤的防撞装置", "label": {"keyword": {"防撞装置": [[11, 14]]}}}
{"text": "一种防治朱砂叶螨的植物性杀螨剂及其制备方法和应用", "label": {"keyword": {"防治": [[2, 3]]}}}
{"text": "风光互补电站有功功率智能控制方法", "label": {"keyword": {"智能控制方法": [[10, 15]]}}}
{"text": "一种具有活体组织显影功能的锌络合物双光子吸收材料及其制备方法", "label": {"keyword": {"双光子吸收": [[17, 21]]}}}
{"text": "钙铝化合物三步处理高浓度含磷废水", "label": {"keyword": {"含磷废水": [[12, 15]]}}}
{"text": "光初始辐射强度校准方法,装置和系统", "label": {"keyword": {"强度校准": [[5, 8]]}}}
{"text": "微波波段的偏振不敏感六波段超材料吸收体", "label": {"keyword": {"超材料吸收体": [[13, 18]]}}}
{"text": "一种可卷曲的太阳能无线充电器", "label": {"keyword": {"电器": [[12, 13]]}}}
{"text": "一种性能有保证的特厚板控轧控冷工艺", "label": {"keyword": {"控轧控冷工艺": [[11, 16]], "控冷工艺": [[13, 16]], "控轧控冷": [[11, 14]]}}}
{"text": "伪匹配高电子迁移率晶体管及其制造方法", "label": {"keyword": {"高电子迁移率晶体管": [[3, 11]], "高电子迁移率": [[3, 8]]}}}
{"text": "一种基于碳纳米管和聚偏二氟乙烯的有机PTC材料", "label": {"keyword": {"聚偏二氟乙烯": [[9, 14]]}}}
{"text": "基于脑机接口的机械臂控制系统及运动指令控制方案", "label": {"keyword": {"脑机接口": [[2, 5]]}}}
{"text": "高压断路器液压操作机构油泵电机控制电路", "label": {"keyword": {"液压操作机构": [[5, 10]], "电机控制电路": [[13, 18]], "高压断路器": [[0, 4]], "高压断路器": [[0, 4]]}}}
{"text": "基于压力振荡的页岩气水平井作业装置", "label": {"keyword": {"页岩气水平井": [[7, 12]]}}}
{"text": "负载纳米金介孔材料包覆量子点构建的电化学发光免疫传感器及HIV检测方法", "label": {"keyword": {"电化学发光免疫传感器": [[17, 26]]}}}
{"text": "基于方向直方图统计的目标识别方法待定", "label": {"keyword": {"目标识别": [[10, 13]]}}}
{"text": "氮化碳纳米片催化剂的制备方法及基于上述催化剂的Knoevenagel缩合反应方法", "label": {"keyword": {"缩合反应": [[34, 37]]}}}
{"text": "塑料光纤双挤出模头聚合反应器", "label": {"keyword": {"塑料光纤": [[0, 3]], "塑料光纤": [[0, 3]], "聚合反应": [[9, 12]]}}}
{"text": "基于智能电视的电器控制方法", "label": {"keyword": {"电器": [[7, 8]]}}}
{"text": "中空碳纤维连续抽油杆接头及其自动焊接设备", "label": {"keyword": {"自动焊接设备": [[14, 19]], "连续抽油杆": [[5, 9]]}}}
{"text": "一种汽车绝缘电阻检测系统", "label": {"keyword": {"绝缘电阻": [[4, 7]]}}}
{"text": "一种碲化镉汞表面绝缘层的制备方法", "label": {"keyword": {"碲化镉汞": [[2, 5]]}}}
{"text": "一种Littman结构可调谐外腔半导体激光器", "label": {"keyword": {"外腔半导体激光器": [[14, 21]]}}}
{"text": "高压断路器分合闸时间在线监测装置", "label": {"keyword": {"在线监测装置": [[10, 15]]}}}
{"text": "一种涂层耐磨剂及其制备方法和应用", "label": {"keyword": {"方法和应用": [[11, 15]]}}}
{"text": "一种用于台阶的人体势能转换发电装置", "label": {"keyword": {"发电装置": [[13, 16]]}}}
{"text": "一种含有纳米银粒子的氮化硼薄膜的制备方法", "label": {"keyword": {"纳米银粒子": [[4, 8]], "纳米银粒子": [[4, 8]]}}}
{"text": "一种输送物料的带式输送机料流检测系统及检测方法", "label": {"keyword": {"输送物料": [[2, 5]]}}}
{"text": "电网调度运行过程风险辅助预控系统", "label": {"keyword": {"调度运行": [[2, 5]]}}}
{"text": "一种提高金属氮基复合储氢材料热力学性能的方法", "label": {"keyword": {"储氢材料": [[10, 13]], "储氢材料": [[10, 13]]}}}
{"text": "一种使用化学耗氧量测定仪的催化剂及其制备方法和使用方法", "label": {"keyword": {"化学耗氧量": [[4, 8]]}}}
{"text": "一种便携式土壤表面粗糙度测量装置", "label": {"keyword": {"土壤表面粗糙度": [[5, 11]]}}}
{"text": "薄板激光切割焊接机工件定位光电测控装置", "label": {"keyword": {"测控": [[15, 16]], "测控装置": [[15, 18]], "工件定位": [[9, 12]]}}}
{"text": "一种易于组合安装的高温超导微波谐振器", "label": {"keyword": {"高温超导": [[9, 12]]}}}
{"text": "主流人体呼吸流量与二氧化碳浓度同步监测装置及方法", "label": {"keyword": {"同步监测": [[15, 18]], "二氧化碳浓度": [[9, 14]]}}}
{"text": "含二硫杂环戊烷的顺式新烟碱类及其制备方法和应用", "label": {"keyword": {"方法和应用": [[18, 22]]}}}
{"text": "多级单组分制冷天然气液化系统", "label": {"keyword": {"天然气液化": [[7, 11]]}}}
{"text": "某天然气管道泄漏光纤监测系统光纤传感器安装结构", "label": {"keyword": {"光纤监测": [[8, 11]], "光纤传感": [[14, 17]]}}}
{"text": " IBY及其在疏水性有机物吸附降解中的应用", "label": {"keyword": {"吸附降解": [[13, 16]]}}}
{"text": "阻抗匹配系统和阻抗匹配方法", "label": {"keyword": {"阻抗匹配方法": [[7, 12]]}}}
{"text": "一种负压微波均质喷雾干燥装置及其应用", "label": {"keyword": {"及其应用": [[14, 17]]}}}
{"text": "基于高速伪随机码调制和光子计数的远程激光测距系统", "label": {"keyword": {"伪随机码调制": [[4, 9]]}}}
{"text": "一种低温余热有机朗肯循环发电系统", "label": {"keyword": {"低温余热": [[2, 5]], "发电系统": [[12, 15]]}}}
{"text": "S/X双频双极化微带振荡器/堆叠贴片天线阵列", "label": {"keyword": {"微带振荡器": [[8, 12]], "堆叠贴片天线": [[14, 19]]}}}
{"text": "一种超亲水和水下超疏油陶瓷膜", "label": {"keyword": {"水下超疏油": [[6, 10]]}}}
{"text": "一种基于块自适应直方图移位的可逆信息隐藏方法", "label": {"keyword": {"可逆信息隐藏": [[14, 19]]}}}
{"text": "基于AHP-模糊评价分析的质量评价方法", "label": {"keyword": {"质量评价方法": [[13, 18]]}}}
{"text": "一种具有高自溶霉素产量的基因工程细菌", "label": {"keyword": {"基因工程": [[12, 15]]}}}
{"text": "任意调节二氧化碳流量和泄漏及防扩散系数的方法和标准装置", "label": {"keyword": {"扩散系数": [[15, 18]]}}}
{"text": "一种反应性聚碳酸酯低聚物及其制备方法和应用", "label": {"keyword": {"方法和应用": [[16, 20]]}}}
{"text": "一种蒸汽重整化学再生内燃机", "label": {"keyword": {"内燃机": [[10, 12]], "内燃机": [[10, 12]]}}}
{"text": "三维有序大孔结构氮化碳光催化剂的制备方法", "label": {"keyword": {"大孔结构": [[4, 7]], "三维有序大孔结构": [[0, 7]], "三维有序大孔": [[0, 5]], "三维有序": [[0, 3]]}}}
{"text": "一种燃料电池用软石墨双极板的连续生产方法", "label": {"keyword": {"连续生产": [[14, 17]]}}}
{"text": "一种旋转金属丝网液压万能试验机的保护装置", "label": {"keyword": {"万能试验机": [[10, 14]], "液压万能试验机": [[8, 14]]}}}
{"text": "一种浅色高纯聚苯乙烯磺酸钠阳离子交换树脂的制备方法", "label": {"keyword": {"聚苯乙烯磺酸钠": [[6, 12]], "阳离子交换树脂": [[13, 19]]}}}
{"text": "丰富真菌胞外多糖的发酵分离方法", "label": {"keyword": {"胞外多糖": [[4, 7]]}}}
{"text": "一种中子插入系统及其准直安装方法", "label": {"keyword": {"准直安装": [[10, 13]]}}}
{"text": "通过表面粗糙化实现高光提取效率的氮化物基发光二极管", "label": {"keyword": {"发光二极管": [[20, 24]], "光提取效率": [[10, 14]], "提取效率": [[11, 14]]}}}
{"text": "一种合成革废水回收利用方法", "label": {"keyword": {"合成革废水": [[2, 6]]}}}
{"text": "气固流化床颗粒混合测量装置", "label": {"keyword": {"气固流化床": [[0, 4]]}}}
{"text": "一种利用木薯酒精废水快速制备外碳源的方法", "label": {"keyword": {"木薯酒精废水": [[4, 9]]}}}
{"text": "一种预防腹泻的花生蛋白粉及其制备方法", "label": {"keyword": {"花生蛋白粉": [[7, 11]]}}}
{"text": "智能变电站防误闭锁逻辑自动测试系统", "label": {"keyword": {"自动测试系统": [[11, 16]], "智能变电站": [[0, 4]]}}}
{"text": "一种用于表面声波器件的氧化锌压电薄膜及其制备方法", "label": {"keyword": {"表面声波器件": [[4, 9]], "表面声波器件": [[4, 9]]}}}
{"text": "一种智能温控覆铜板腐蚀设备", "label": {"keyword": {"智能温控": [[2, 5]]}}}
{"text": "一种固态储氢材料及其制备方法", "label": {"keyword": {"固态储氢": [[2, 5]], "固态储氢": [[2, 5]], "储氢材料": [[4, 7]]}}}
{"text": "基于动态疲劳试验机的拟三轴试验装置", "label": {"keyword": {"疲劳试验机": [[4, 8]]}}}
{"text": "一种酶生物燃料电池及其制备方法", "label": {"keyword": {"酶生物燃料电池": [[2, 8]]}}}
{"text": "一种金属酸洗缓蚀剂,其制备方法和应用", "label": {"keyword": {"酸洗缓蚀剂": [[4, 8]]}}}
{"text": "一种同时去除金属离子和有机物的吸附剂制备方法", "label": {"keyword": {"去除金属离子": [[4, 9]]}}}
{"text": "一种多功能微型电火花铣削装置", "label": {"keyword": {"电火花铣削": [[7, 11]]}}}
{"text": "磁共振成像装置和床板组件", "label": {"keyword": {"磁共振成像": [[0, 4]], "磁共振成像": [[0, 4]]}}}
{"text": "一种确定LNG储罐隔震效果的方法", "label": {"keyword": {"隔震效果": [[9, 12]]}}}
{"text": "基于动态控制人工电磁结构材料的相控阵天线", "label": {"keyword": {"电磁结构": [[8, 11]]}}}
{"text": "加替沙星电化学酶联免疫吸附测定试剂盒及其应用", "label": {"keyword": {"联免疫吸附测定": [[8, 14]]}}}
{"text": "基于薄膜的激光强度响应范围测量装置", "label": {"keyword": {"激光强度": [[5, 8]]}}}
{"text": "基于主动悬挂辅助的汽车防抱死制动系统非线性鲁棒控制方法", "label": {"keyword": {"汽车防抱死制动系统": [[9, 17]], "非线性鲁棒控制": [[18, 24]], "鲁棒控制方法": [[21, 26]], "线性鲁棒控制": [[19, 24]], "防抱死制动系统": [[11, 17]]}}}
{"text": "苯乙烯存在下苯乙炔的高选择性加氢方法", "label": {"keyword": {"选择性加氢": [[11, 15]]}}}
{"text": "一种抗菌静电纺纤维膜的制备方法", "label": {"keyword": {"电纺纤维膜": [[5, 9]]}}}
{"text": "高压直流配电装置及其控制方法", "label": {"keyword": {"配电装置": [[4, 7]]}}}
{"text": "中小型液压机安全螺栓装置", "label": {"keyword": {"中小型": [[0, 2]]}}}
{"text": "电力基础设施现场工作人员识别背心", "label": {"keyword": {"电力基础设施": [[0, 5]]}}}
{"text": "FAST射电望远镜健康监测系统", "label": {"keyword": {"健康监测系统": [[9, 14]]}}}
{"text": "一种环保型PVC用钙锌复合热稳定剂", "label": {"keyword": {"环保型": [[2, 4]], "钙锌复合热稳定剂": [[9, 16]], "复合热稳定剂": [[11, 16]]}}}
{"text": "一种带有治疗毛巾的一次性胃镜检查牙垫", "label": {"keyword": {"胃镜检查": [[12, 15]]}}}
{"text": "海洋贝类养殖碳汇评价模型的构建方法及应用", "label": {"keyword": {"贝类养殖": [[2, 5]]}}}
{"text": "滑动散射中心方位相位误差的一种计算方法", "label": {"keyword": {"滑动散射中心": [[0, 5]]}}}
{"text": "脉冲激光测距仪发射驱动电源", "label": {"keyword": {"脉冲激光测距仪": [[0, 6]]}}}
{"text": "一种用于减少 FCC 再生烟气中NOx排放的组合物", "label": {"keyword": {"再生烟气": [[11, 14]]}}}
{"text": "一种小型垃圾焚烧炉余热发电系统", "label": {"keyword": {"发电系统": [[11, 14]], "余热发电": [[9, 12]], "余热发电系统": [[9, 14]]}}}
{"text": "一种轻质耐高温碳纤维金属混合层压板", "label": {"keyword": {"耐高温": [[4, 6]]}}}
{"text": "认知无线网络中的一种多用户动态频谱共享方法", "label": {"keyword": {"认知无线网络": [[0, 5]], "动态频谱共享": [[13, 18]]}}}
{"text": "一种杏鲍菇真空预冷保鲜技术", "label": {"keyword": {"保鲜技术": [[9, 12]]}}}
{"text": "双功能催化剂及其在安息香脱氢/氧化制备苯偶酰中的应用", "label": {"keyword": {"双功能催化剂": [[0, 5]]}}}
{"text": "一种利用模板制备光子晶体塑料闪烁体的方法", "label": {"keyword": {"塑料闪烁体": [[12, 16]]}}}
{"text": "钢管混凝土柱高层建筑框架结构优化设计方法", "label": {"keyword": {"结构优化": [[12, 15]]}}}
{"text": "一种合成硫代氨基酸衍生物的方法", "label": {"keyword": {"氨基酸衍生物": [[6, 11]]}}}
{"text": "特高压输电线路绝缘子串带电更换成套工具及其使用方法", "label": {"keyword": {"特高压输电线路": [[0, 6]], "高压输电线路": [[1, 6]], "高压输电线路": [[1, 6]], "高压输电线路": [[1, 6]]}}}
{"text": "一种双金属海藻酸钠/羧甲基纤维素双功能微球吸附材料及其制备方法", "label": {"keyword": {"功能微球": [[17, 20]], "羧甲基纤维素": [[10, 15]], "羧甲基纤维素": [[10, 15]]}}}
{"text": "一种下肢康复自动康复装置", "label": {"keyword": {"下肢康复": [[2, 5]]}}}
{"text": "一种木质素综合利用方法", "label": {"keyword": {"综合利用": [[5, 8]]}}}
{"text": "一种通过挤压莰烯/氮化硅冷冻体制备定向多孔氮化硅陶瓷的方法", "label": {"keyword": {"氮化硅陶瓷": [[21, 25]], "氮化硅陶瓷": [[21, 25]], "多孔氮化硅陶瓷": [[19, 25]], "多孔氮化硅": [[19, 23]], "多孔氮化硅陶瓷": [[19, 25]]}}}
{"text": "一种高抗凝聚苯乙烯微球及其制备方法和应用", "label": {"keyword": {"聚苯乙烯微球": [[5, 10]]}}}
{"text": "一种智能网联汽车环境感知系统的多雷达数据融合方法", "label": {"keyword": {"环境感知": [[8, 11]]}}}
{"text": "一种用于探测海底热液的独立灯丝三电极传感系统", "label": {"keyword": {"海底热液": [[6, 9]]}}}
{"text": "高压水射流旋转冲击水蚀实验装置", "label": {"keyword": {"高压水射流": [[0, 4]]}}}
{"text": "一种矿用TBM运输系统", "label": {"keyword": {"运输系统": [[7, 10]]}}}
{"text": "一种采用紫外LED阵列光源的手持梯形多功能荧光检测箱", "label": {"keyword": {"荧光检测": [[21, 24]]}}}
{"text": "一种应用层协议识别特征挖掘方法", "label": {"keyword": {"应用层协议": [[2, 6]]}}}
{"text": "超薄空心轴光电轴编码器", "label": {"keyword": {"光电轴编码器": [[5, 10]]}}}
{"text": "断路器及电机故障智能监控保护装置", "label": {"keyword": {"智能监控": [[8, 11]], "监控保护": [[10, 13]]}}}
{"text": "一种具有吸附性能的微孔硼钒酸盐化合物及其制备方法", "label": {"keyword": {"吸附性能": [[4, 7]]}}}
{"text": "富里酸-异氰酸酯改性脲醛树脂粘合剂及其制备方法", "label": {"keyword": {"脲醛树脂粘合剂": [[10, 16]]}}}
{"text": "长春瑞滨固体脂质纳米粒及其冻干制剂及其制备方法", "label": {"keyword": {"冻干制剂": [[13, 16]]}}}
{"text": "含长支链结构的高熔体强度聚丙烯及其制备方法", "label": {"keyword": {"高熔体强度聚丙烯": [[7, 14]]}}}
{"text": "频率输出型传感器自动频率补偿电路及方法", "label": {"keyword": {"频率补偿": [[10, 13]]}}}
{"text": "一种包括多端柔性直流输电系统的电网运行控制系统和方法", "label": {"keyword": {"柔性直流输电系统": [[6, 13]], "运行控制系统": [[17, 22]], "直流输电系统": [[8, 13]], "多端柔性直流输电系统": [[4, 13]]}}}
{"text": "Power ERP商业智能仿真系统", "label": {"keyword": {"商业智能": [[9, 12]]}}}
{"text": "一种新型IZ-shGITRL融合蛋白及其制备方法和应用", "label": {"keyword": {"方法和应用": [[22, 26]]}}}
{"text": "循环流化床锅炉自激串联电旋风分离装置及其分离方法", "label": {"keyword": {"循环流化床锅炉": [[0, 6]], "循环流化床": [[0, 4]]}}}
{"text": "核磁共振水检测仪充放电功率测试装置", "label": {"keyword": {"充放电": [[8, 10]], "核磁共振": [[0, 3]]}}}
{"text": "一种基于Gabor直方图熵的图像分割方法", "label": {"keyword": {"图像分割方法": [[14, 19]]}}}
{"text": "一种实现深度阳离子光聚合的方法及组合物", "label": {"keyword": {"阳离子光聚合": [[6, 11]]}}}
{"text": "一种基于最大似然估计的配电网状态估计方法", "label": {"keyword": {"最大似然估计": [[4, 9]]}}}
{"text": "生活在水中的微异养甲藻的分离纯化方法", "label": {"keyword": {"异养甲藻": [[7, 10]]}}}
{"text": "基于有源全补偿消弧控制的相似单相接地故障选线方法", "label": {"keyword": {"单相接地故障": [[14, 19]], "单相接地故障": [[14, 19]]}}}
{"text": "全面质量监督关键环节质量评价体系", "label": {"keyword": {"质量评价体系": [[10, 15]]}}}
{"text": "基于石墨烯电光调制的有源调Q光纤激光器", "label": {"keyword": {"电光调制": [[5, 8]]}}}
{"text": "柔性染料敏化太阳能电池纳米晶薄膜的制备方法", "label": {"keyword": {"染料敏化太阳能电池": [[2, 10]], "柔性染料敏化太阳能电池": [[0, 10]], "敏化太阳能电池": [[4, 10]]}}}
{"text": "一种单滑块变质心控制飞行器的动态稳定性确定方法", "label": {"keyword": {"稳定性确定": [[16, 20]]}}}
{"text": "一种蚕茧天然色素色牢度的鉴别方法", "label": {"keyword": {"鉴别方法": [[12, 15]]}}}
{"text": "一种无线传感器网络的低能耗覆盖优化算法", "label": {"keyword": {"优化算法": [[15, 18]]}}}
